MANIFEST.in
README.rst
bootstrap.py
buildout.cfg
setup.py
test-plone-4.2.x.cfg
test-plone-4.x.cfg
travis.cfg
versions.cfg
collective/__init__.py
collective.dancing.egg-info/PKG-INFO
collective.dancing.egg-info/SOURCES.txt
collective.dancing.egg-info/dependency_links.txt
collective.dancing.egg-info/entry_points.txt
collective.dancing.egg-info/namespace_packages.txt
collective.dancing.egg-info/not-zip-safe
collective.dancing.egg-info/requires.txt
collective.dancing.egg-info/top_level.txt
collective/dancing/__init__.py
collective/dancing/browser.txt
collective/dancing/channel.py
collective/dancing/channel.txt
collective/dancing/collector.py
collective/dancing/collector.txt
collective/dancing/composer.py
collective/dancing/composer.txt
collective/dancing/configure.zcml
collective/dancing/contentrules.py
collective/dancing/cronrunner.py
collective/dancing/events.py
collective/dancing/interfaces.py
collective/dancing/mail.zcml
collective/dancing/overrides.zcml
collective/dancing/permissions.zcml
collective/dancing/portlets.txt
collective/dancing/rebuild_i18n.sh
collective/dancing/setuphandlers.py
collective/dancing/subscribe.py
collective/dancing/tests.py
collective/dancing/transform.py
collective/dancing/transform.txt
collective/dancing/upgrades.py
collective/dancing/upgrades.zcml
collective/dancing/utils.py
collective/dancing/Extensions/install.py
collective/dancing/browser/__init__.py
collective/dancing/browser/channel-crud-row.pt
collective/dancing/browser/channel-crud-table.pt
collective/dancing/browser/channel-form-master.pt
collective/dancing/browser/channel.py
collective/dancing/browser/collector.py
collective/dancing/browser/composer-html-confirm.pt
collective/dancing/browser/composer-html-forgot.pt
collective/dancing/browser/composer-html.pt
collective/dancing/browser/composer.py
collective/dancing/browser/configure.zcml
collective/dancing/browser/controlpanel-links.pt
collective/dancing/browser/controlpanel.pt
collective/dancing/browser/controlpanel.py
collective/dancing/browser/form-with-subforms.pt
collective/dancing/browser/form.pt
collective/dancing/browser/interfaces.py
collective/dancing/browser/jobs.pt
collective/dancing/browser/prettysubscriptions.pt
collective/dancing/browser/prettysubscriptionsform.pt
collective/dancing/browser/preview.pt
collective/dancing/browser/preview.py
