Metadata-Version: 2.1
Name: collective.dancing
Version: 1.2
Summary: The all-singing all-dancing newsletter add-on for Plone.
Home-page: http://plone.org/products/dancing
Author: Daniel Nouri, Thomas Clement Mogensen and contributors
Author-email: singing-dancing@googlegroups.com
License: GPL
Download-URL: 
Keywords: zope plone notification newsletter
Platform: UNKNOWN
Classifier: Framework :: Plone
Classifier: Framework :: Plone :: 4.3
Classifier: Framework :: Plone :: 4.2
Classifier: Framework :: Zope2
Classifier: Programming Language :: Python
Provides-Extra: test
